{
  "parent": "minecraft:recipes/root",
  "criteria": {
    "has_poppy_ii": {
      "conditions": {
        "items": [
          {
            "items": [
              "compressed_items:poppy_ii"
            ]
          }
        ]
      },
      "trigger": "minecraft:inventory_changed"
    },
    "has_the_recipe": {
      "conditions": {
        "recipe": "minecraft:poppy_ii_unpack"
      },
      "trigger": "minecraft:recipe_unlocked"
    }
  },
  "requirements": [
    [
      "has_poppy_ii",
      "has_the_recipe"
    ]
  ],
  "rewards": {
    "recipes": [
      "minecraft:poppy_ii_unpack"
    ]
  }
}